pretix_iyzico/__init__.py
pretix_iyzico/apps.py
pretix_iyzico/payment.py
pretix_iyzico/signals.py
pretix_iyzico/urls.py
pretix_iyzico/views.py
pretix_iyzico/locale/de/LC_MESSAGES/django.mo
pretix_iyzico/locale/de/LC_MESSAGES/django.po
pretix_iyzico/locale/de_Informal/.gitkeep
pretix_iyzico/locale/de_Informal/LC_MESSAGES/django.mo
pretix_iyzico/locale/de_Informal/LC_MESSAGES/django.po
pretix_iyzico/static/pretix_iyzico/.gitkeep
pretix_iyzico/templates/pretix_iyzico/.gitkeep
pretix_iyzico/templates/pretix_iyzico/checkout_confirm.html
pretix_iyzico/templates/pretix_iyzico/checkout_payment_form.html
pretix_iyzico-1.0.0.dist-info/licenses/LICENSE
pretix_iyzico-1.0.0.dist-info/METADATA
pretix_iyzico-1.0.0.dist-info/WHEEL
pretix_iyzico-1.0.0.dist-info/entry_points.txt
pretix_iyzico-1.0.0.dist-info/top_level.txt
pretix_iyzico-1.0.0.dist-info/RECORD
