Metadata-Version: 2.4
Name: pretix-iyzico
Version: 1.0.0
Summary: Pretix payment provider plugin for iyzico integration
Author-email: Emircan Kartal <emircankartal1@gmail.com>, Ata Tan Dağıdır <atadagidir@gmail.com>
Maintainer-email: Fidelio Software <emircankartal1@gmail.com>
License: Apache-2.0
Project-URL: homepage, https://github.com/EmircanKartal/pretix-iyzico
Project-URL: repository, https://github.com/EmircanKartal/pretix-iyzico
Keywords: pretix
License-File: LICENSE
Requires-Dist: requests>=2.25.0
Requires-Dist: iyzipay>=1.0.45
Dynamic: license-file
